[
  {
    "client": "llama31_8b_standard",
    "concept": "truck",
    "domain": "temperature",
    "measurement": "kelvin",
    "dimension": "temperature",
    "format": "range",
    "response": "{\n  \"min_temperature\": 233.15,\n  \"max_temperature\": 353.15\n}"
  },
  {
    "client": "llama31_8b_standard",
    "concept": "truck",
    "domain": "temperature",
    "measurement": "kelvin",
    "dimension": "temperature",
    "format": "range",
    "response": "{\n  \"min_temperature\": 255.372,\n  \"max_temperature\": 313.15\n}"
  },
  {
    "client": "llama31_8b_standard",
    "concept": "truck",
    "domain": "temperature",
    "measurement": "kelvin",
    "dimension": "temperature",
    "format": "range",
    "response": "{\n  \"min_temperature\": 233.15,\n  \"max_temperature\": 313.15\n}"
  },
  {
    "client": "llama31_8b_standard",
    "concept": "truck",
    "domain": "temperature",
    "measurement": "kelvin",
    "dimension": "temperature",
    "format": "range",
    "response": "{\n  \"min_temperature\": 233.15,\n  \"max_temperature\": 333.15\n}"
  },
  {
    "client": "llama31_8b_standard",
    "concept": "truck",
    "domain": "temperature",
    "measurement": "kelvin",
    "dimension": "temperature",
    "format": "range",
    "response": "{\n    \"min_temperature\": 278.15,\n    \"max_temperature\": 333.15\n}"
  },
  {
    "client": "llama31_8b_standard",
    "concept": "truck",
    "domain": "temperature",
    "measurement": "kelvin",
    "dimension": "temperature",
    "format": "range",
    "response": "{\n  \"min_temperature\": 230.15,\n  \"max_temperature\": 343.15\n}"
  },
  {
    "client": "llama31_8b_standard",
    "concept": "truck",
    "domain": "temperature",
    "measurement": "kelvin",
    "dimension": "temperature",
    "format": "range",
    "response": "{\n    \"min_temperature\": 233.15,\n    \"max_temperature\": 313.15\n}"
  },
  {
    "client": "llama31_8b_standard",
    "concept": "truck",
    "domain": "temperature",
    "measurement": "kelvin",
    "dimension": "temperature",
    "format": "range",
    "response": "{\n    \"min_temperature\": 233.15,\n    \"max_temperature\": 333.15\n}"
  },
  {
    "client": "llama31_8b_standard",
    "concept": "truck",
    "domain": "temperature",
    "measurement": "kelvin",
    "dimension": "temperature",
    "format": "range",
    "response": "{\n  \"min_temperature\": 233.15,\n  \"max_temperature\": 383.15\n}"
  },
  {
    "client": "llama31_8b_standard",
    "concept": "truck",
    "domain": "temperature",
    "measurement": "kelvin",
    "dimension": "temperature",
    "format": "range",
    "response": "{\n  \"min_temperature\": 233.15,\n  \"max_temperature\": 333.15\n}"
  },
  {
    "client": "llama31_8b_standard",
    "concept": "truck",
    "domain": "temperature",
    "measurement": "kelvin",
    "dimension": "temperature",
    "format": "range",
    "response": "{\n    \"min_temperature\": 233.15,\n    \"max_temperature\": 333.15\n}"
  },
  {
    "client": "llama31_8b_standard",
    "concept": "truck",
    "domain": "temperature",
    "measurement": "kelvin",
    "dimension": "temperature",
    "format": "range",
    "response": "{\n    \"min_temperature\": 233.15,\n    \"max_temperature\": 338.15\n}"
  },
  {
    "client": "llama31_8b_standard",
    "concept": "truck",
    "domain": "temperature",
    "measurement": "kelvin",
    "dimension": "temperature",
    "format": "range",
    "response": "{\n    \"min_temperature\": 253.15,\n    \"max_temperature\": 393.15\n}"
  },
  {
    "client": "llama31_8b_standard",
    "concept": "truck",
    "domain": "temperature",
    "measurement": "kelvin",
    "dimension": "temperature",
    "format": "range",
    "response": "{\n    \"min_temperature\": 230,\n    \"max_temperature\": 370\n}"
  },
  {
    "client": "llama31_8b_standard",
    "concept": "truck",
    "domain": "temperature",
    "measurement": "kelvin",
    "dimension": "temperature",
    "format": "range",
    "response": "{\n    \"min_temperature\": 223,\n    \"max_temperature\": 343\n}"
  },
  {
    "client": "llama31_8b_standard",
    "concept": "truck",
    "domain": "temperature",
    "measurement": "kelvin",
    "dimension": "temperature",
    "format": "range",
    "response": "{\n  \"min_temperature\": 243.15,\n  \"max_temperature\": 343.15\n}"
  },
  {
    "client": "llama31_8b_standard",
    "concept": "truck",
    "domain": "temperature",
    "measurement": "kelvin",
    "dimension": "temperature",
    "format": "range",
    "response": "{\n  \"min_temperature\": 253.15,\n  \"max_temperature\": 313.15\n}"
  },
  {
    "client": "llama31_8b_standard",
    "concept": "truck",
    "domain": "temperature",
    "measurement": "kelvin",
    "dimension": "temperature",
    "format": "range",
    "response": "{\n  \"min_temperature\": 233.15,\n  \"max_temperature\": 313.15\n}"
  },
  {
    "client": "llama31_8b_standard",
    "concept": "truck",
    "domain": "temperature",
    "measurement": "kelvin",
    "dimension": "temperature",
    "format": "range",
    "response": "{\n  \"min_temperature\": 223.15,\n  \"max_temperature\": 313.15\n}"
  },
  {
    "client": "llama31_8b_standard",
    "concept": "truck",
    "domain": "temperature",
    "measurement": "kelvin",
    "dimension": "temperature",
    "format": "range",
    "response": "{\n  \"min_temperature\": 223.15,\n  \"max_temperature\": 343.15\n}"
  }
]