[
  {
    "client": "llama2_7b_chat",
    "concept": "fork",
    "domain": "pattern",
    "measurement": "",
    "dimension": "",
    "format": "avg",
    "response": "{\n\"patterns\": [\n\"fork as utensil\",\n\"fork as eating implement\",\n\"fork as food serving tool\"\n]\n}"
  },
  {
    "client": "llama2_7b_chat",
    "concept": "fork",
    "domain": "pattern",
    "measurement": "",
    "dimension": "",
    "format": "avg",
    "response": "{\n  \"patterns\": [\n    {\n      \"name\": \"fork-in-hand\",\n      \"description\": \"Holding a fork in one's hand, ready to use it to eat food.\"\n    },\n    {\n      \"name\": \"fork-on-table\",\n      \"description\": \"placing a fork on a table, ready to use it to eat food.\"\n    },\n    {\n      \"name\": \"fork-in-bowl\",\n      \"description\": \"placing a fork in a bowl, ready to use it to eat food.\"\n    }\n  ]\n}\n"
  },
  {
    "client": "llama2_7b_chat",
    "concept": "fork",
    "domain": "pattern",
    "measurement": "",
    "dimension": "",
    "format": "avg",
    "response": "{\n\"patterns\": [\n\"eat with fork\",\n\"use fork to serve food\",\n\"fork food onto plate\",\n\"serve food with fork\",\n\"fork in left hand\",\n\"fork in right hand\"\n]\n}\n"
  },
  {
    "client": "llama2_7b_chat",
    "concept": "fork",
    "domain": "pattern",
    "measurement": "",
    "dimension": "",
    "format": "avg",
    "response": "{\n\"patterns\": [\n{\n\"name\": \"serve\",\n\"pattern\": \"use a fork to serve food from a plate or bowl to a plate or bowl\"\n},\n{\n\"name\": \"eat\",\n\"pattern\": \"use a fork to eat food from a plate or bowl\"\n}\n]\n}\n"
  },
  {
    "client": "llama2_7b_chat",
    "concept": "fork",
    "domain": "pattern",
    "measurement": "",
    "dimension": "",
    "format": "avg",
    "response": "{\n\"pattern\": [\n\"fork to plate\",\n\"fork to mouth\",\n\"fork to table\",\n\"fork to plate\",\n\"fork to fork\"\n]\n}\n"
  },
  {
    "client": "llama2_7b_chat",
    "concept": "fork",
    "domain": "pattern",
    "measurement": "",
    "dimension": "",
    "format": "avg",
    "response": "{\n\"pattern\": [\"fork\", \"cutlery\", \"serving\", \"eating\"]\n}\n"
  },
  {
    "client": "llama2_7b_chat",
    "concept": "fork",
    "domain": "pattern",
    "measurement": "",
    "dimension": "",
    "format": "avg",
    "response": "{\n\"patterns\": [\n    {\n        \"name\": \"serving\",\n        \"description\": \"Use the fork to serve food to others\",\n        \"examples\": [\n            {\n                \"text\": \"She used a fork to serve the salad to her guests.\",\n                \"context\": \"dining\"\n            },\n            {\n                \"text\": \"He used a fork to serve the roast beef to his family.\",\n                \"context\": \"dining\"\n            }\n        ]\n    },\n    {\n        \"name\": \"eating\",\n        \"description\": \"Use the fork to eat food\",\n        \"examples\": [\n            {\n                \"text\": \"She used a fork to eat her breakfast.\",\n                \"context\": \"breakfast\"\n            },\n            {\n                \"text\": \"He used a fork to eat his dinner.\",\n                \"context\": \"dinner\"\n            }\n        ]\n    },\n    {\n        \"name\": \"stirring\",\n        \"description\": \"Use the fork to stir food\",\n        \"examples\": [\n            {\n                \"text\": \"She used a fork to stir the soup.\",\n                \"context\": \"cooking\"\n            },\n            {\n                \"text\": \"He used a fork to stir the eggs.\",\n                \"context\": \"cooking\"\n            }\n        ]\n    }\n]\n}\n"
  },
  {
    "client": "llama2_7b_chat",
    "concept": "fork",
    "domain": "pattern",
    "measurement": "",
    "dimension": "",
    "format": "avg",
    "response": "{\n  \"patterns\": [\n    {\n      \"name\": \"Fork in hand\",\n      \"description\": \"Holding a fork in your hand, ready to use it to eat food\",\n      \"entities\": [\n        {\n          \"name\": \"Fork\",\n          \"description\": \"Cutlery used for serving and eating food\"\n        }\n      ]\n    },\n    {\n      \"name\": \"Fork on plate\",\n      \"description\": \"A fork placed on a plate, ready to be used to eat food\",\n      \"entities\": [\n        {\n          \"name\": \"Fork\",\n          \"description\": \"Cutlery used for serving and eating food\"\n        },\n        {\n          \"name\": \"Plate\",\n          \"description\": \"Dish used to serve and eat food\"\n        }\n      ]\n    },\n    {\n      \"name\": \"Fork in bowl\",\n      \"description\": \"A fork placed in a bowl, ready to be used to eat food\",\n      \"entities\": [\n        {\n          \"name\": \"Fork\",\n          \"description\": \"Cutlery used for serving and eating food\"\n        },\n        {\n          \"name\": \"Bowl\",\n          \"description\": \"Container used to hold food\"\n        }\n      ]\n    }\n  ]\n}"
  },
  {
    "client": "llama2_7b_chat",
    "concept": "fork",
    "domain": "pattern",
    "measurement": "",
    "dimension": "",
    "format": "avg",
    "response": "{\n  \"pattern\": [\"fork\"]\n}\n"
  },
  {
    "client": "llama2_7b_chat",
    "concept": "fork",
    "domain": "pattern",
    "measurement": "",
    "dimension": "",
    "format": "avg",
    "response": "{\n\"pattern\": [\n    \"fork food\",\n    \"serve with fork\",\n    \"eat with fork\",\n    \"use fork to eat\",\n    \"fork for serving\"\n]\n}\n"
  },
  {
    "client": "llama2_7b_chat",
    "concept": "fork",
    "domain": "pattern",
    "measurement": "",
    "dimension": "",
    "format": "avg",
    "response": "{\n  \"patterns\": [\n    {\n      \"name\": \"fork-and-knife\",\n      \"description\": \"Hold fork in one hand and knife in the other, used for formal dining\",\n      \"variations\": [\n        {\n          \"name\": \"fork-and-spoon\",\n          \"description\": \"Hold fork in one hand and spoon in the other, used for eating soups or cereals\",\n          \"variations\": []\n        }\n      ]\n    },\n    {\n      \"name\": \"fork-and-chopsticks\",\n      \"description\": \"Hold fork in one hand and chopsticks in the other, used for Asian cuisine\",\n      \"variations\": []\n    }\n  ]\n}\n"
  },
  {
    "client": "llama2_7b_chat",
    "concept": "fork",
    "domain": "pattern",
    "measurement": "",
    "dimension": "",
    "format": "avg",
    "response": "{\n  \"patterns\": [\n    {\n      \"name\": \"fork- food\",\n      \"description\": \"Use a fork to serve and eat food\",\n      \"example\": \"She used a fork to eat her salad\",\n      \"entities\": [\n        {\n          \"name\": \"fork\",\n          \"description\": \"Cutlery used for serving and eating food\"\n        },\n        {\n          \"name\": \"food\",\n          \"description\": \"Edible substance\"\n        }\n      ]\n    }\n  ]\n}"
  },
  {
    "client": "llama2_7b_chat",
    "concept": "fork",
    "domain": "pattern",
    "measurement": "",
    "dimension": "",
    "format": "avg",
    "response": "{\n\"patterns\": [\n    {\n        \"name\": \"serve\",\n        \"description\": \"use the fork to serve food\",\n        \"examples\": [\n            \"She picked up the fork and used it to serve the salad.\"\n        ]\n    },\n    {\n        \"name\": \"eat\",\n        \"description\": \"use the fork to eat food\",\n        \"examples\": [\n            \"He took a bite of his steak with his fork.\"\n        ]\n    },\n    {\n        \"name\": \"fork\",\n        \"description\": \"the cutlery used for serving and eating food\",\n        \"examples\": [\n            \"The fork is a utensil used for both serving and eating food.\"\n        ]\n    }\n]\n}\n"
  },
  {
    "client": "llama2_7b_chat",
    "concept": "fork",
    "domain": "pattern",
    "measurement": "",
    "dimension": "",
    "format": "avg",
    "response": "{\n\"pattern\": [\n\"fork to plate\",\n\"fork to mouth\",\n\"fork to knife\",\n\"fork to spoon\"\n]\n}"
  },
  {
    "client": "llama2_7b_chat",
    "concept": "fork",
    "domain": "pattern",
    "measurement": "",
    "dimension": "",
    "format": "avg",
    "response": "{\n\"pattern\": [\n\"fork to eat\",\n\"fork to serve\",\n\"fork to eat with\",\n\"fork and knife\",\n\"fork and spoon\"\n]\n}\n"
  },
  {
    "client": "llama2_7b_chat",
    "concept": "fork",
    "domain": "pattern",
    "measurement": "",
    "dimension": "",
    "format": "avg",
    "response": "{\n  \"patterns\": [\n    {\n      \"name\": \"fork-and-knife\",\n      \"description\": \"Used for serving and eating food, typically in a formal setting\",\n      \"entails\": [\n        {\n          \"name\": \"fork\",\n          \"description\": \"Used for picking up and transporting food to the mouth\",\n          \"entails\": [\n            {\n              \"name\": \"lift\",\n              \"description\": \"Used to lift food from a plate or bowl to the mouth\",\n              \"entails\": []\n            }\n          ]\n        },\n        {\n          \"name\": \"knife\",\n          \"description\": \"Used for cutting food into bite-sized pieces\",\n          \"entails\": []\n        }\n      ]\n    }\n  ]\n}\n"
  },
  {
    "client": "llama2_7b_chat",
    "concept": "fork",
    "domain": "pattern",
    "measurement": "",
    "dimension": "",
    "format": "avg",
    "response": "{\n\"pattern\": [\n\"fork to plate\",\n\"fork to mouth\",\n\"fork to spoon\",\n\"fork to bowl\"\n]\n}\n"
  },
  {
    "client": "llama2_7b_chat",
    "concept": "fork",
    "domain": "pattern",
    "measurement": "",
    "dimension": "",
    "format": "avg",
    "response": "{\n  \"patterns\": [\n    {\n      \"name\": \"serving\",\n      \"description\": \"Using the fork to serve food\",\n      \"example\": \"She used a fork to serve the soup.\"\n    },\n    {\n      \"name\": \"eating\",\n      \"description\": \"Using the fork to eat food\",\n      \"example\": \"He used a fork to eat his salad.\"\n    },\n    {\n      \"name\": \"stirring\",\n      \"description\": \"Using the fork to stir food\",\n      \"example\": \"She used a fork to stir the potatoes.\"\n    },\n    {\n      \"name\": \"cutting\",\n      \"description\": \"Using the fork to cut food\",\n      \"example\": \"He used a fork to cut the steak.\"\n    }\n  ]\n}\n"
  },
  {
    "client": "llama2_7b_chat",
    "concept": "fork",
    "domain": "pattern",
    "measurement": "",
    "dimension": "",
    "format": "avg",
    "response": "{\n  \"patterns\": [\n    {\n      \"name\": \"Serving food\",\n      \"description\": \"Use the fork to serve food from a plate to a plate or directly to a person's mouth.\"\n    },\n    {\n      \"name\": \"Eating food\",\n      \"description\": \"Use the fork to eat food from a plate.\"\n    },\n    {\n      \"name\": \"Flipping food\",\n      \"description\": \"Use the fork to flip food, such as pancakes or eggs, while cooking.\"\n    },\n    {\n      \"name\": \"Stirring food\",\n      \"description\": \"Use the fork to stir food, such as soup or pasta, while cooking.\"\n    }\n  ]\n}\n"
  },
  {
    "client": "llama2_7b_chat",
    "concept": "fork",
    "domain": "pattern",
    "measurement": "",
    "dimension": "",
    "format": "avg",
    "response": "{\n  \"pattern\": [\n    \"serve food with fork\",\n    \"eat with fork\",\n    \"use fork to pick up food\",\n    \"fork as utensil for eating\"\n  ]\n}\n"
  }
]