[
  {
    "client": "phi_4k_instruct",
    "concept": "skis",
    "domain": "size",
    "measurement": "inches",
    "dimension": "height",
    "format": "range",
    "response": "{\n  \"min_size\": 140,\n  \"max_size\": 225\n}\n"
  },
  {
    "client": "phi_4k_instruct",
    "concept": "skis",
    "domain": "size",
    "measurement": "inches",
    "dimension": "height",
    "format": "range",
    "response": "{\n  \"min_size\": 75,\n  \"max_size\": 225\n}\n  \t\t\t\t\t\t\t\t\t\t\t\t\t\t\t\t\t\t"
  },
  {
    "client": "phi_4k_instruct",
    "concept": "skis",
    "domain": "size",
    "measurement": "inches",
    "dimension": "height",
    "format": "range",
    "response": "{\n  \"min_size\": 24,\n  \"max_size\": 225\n}\n"
  },
  {
    "client": "phi_4k_instruct",
    "concept": "skis",
    "domain": "size",
    "measurement": "inches",
    "dimension": "height",
    "format": "range",
    "response": "{\n  \"min_size\": 100,\n  \"max_size\": 250\n}\n "
  },
  {
    "client": "phi_4k_instruct",
    "concept": "skis",
    "domain": "size",
    "measurement": "inches",
    "dimension": "height",
    "format": "range",
    "response": "{\n  \"min_size\": 16.0,\n  \"max_size\": 24.0\n}\n   "
  },
  {
    "client": "phi_4k_instruct",
    "concept": "skis",
    "domain": "size",
    "measurement": "inches",
    "dimension": "height",
    "format": "range",
    "response": "{\n  \"min_size\": 24,\n  \"max_size\": 28\n}\n   "
  },
  {
    "client": "phi_4k_instruct",
    "concept": "skis",
    "domain": "size",
    "measurement": "inches",
    "dimension": "height",
    "format": "range",
    "response": "{\n  \"min_size\": 24,\n  \"max_size\": 27\n}\n"
  },
  {
    "client": "phi_4k_instruct",
    "concept": "skis",
    "domain": "size",
    "measurement": "inches",
    "dimension": "height",
    "format": "range",
    "response": "{\n  \"min_size\": 75,\n  \"max_size\": 225\n}\n  \t\t\t\t\t\t\t\t\t\t\t\t\t\t\t\t\t\t"
  },
  {
    "client": "phi_4k_instruct",
    "concept": "skis",
    "domain": "size",
    "measurement": "inches",
    "dimension": "height",
    "format": "range",
    "response": "{\n  \"min_size\": 80,\n  \"max_size\": 225\n}\n  \t\t\t\t\t\t\t\t\t\t\t\t\t\t\t\t\t\t"
  },
  {
    "client": "phi_4k_instruct",
    "concept": "skis",
    "domain": "size",
    "measurement": "inches",
    "dimension": "height",
    "format": "range",
    "response": "{\n  \"min_size\": 14,\n  \"max_size\": 22\n}\n"
  },
  {
    "client": "phi_4k_instruct",
    "concept": "skis",
    "domain": "size",
    "measurement": "inches",
    "dimension": "height",
    "format": "range",
    "response": "{\n  \"min_size\": 24,\n  \"max_size\": 265\n}\n   \t\t\t\t\t\t\t\t\t\t\t\t\t\t\t\t\t"
  },
  {
    "client": "phi_4k_instruct",
    "concept": "skis",
    "domain": "size",
    "measurement": "inches",
    "dimension": "height",
    "format": "range",
    "response": "{\n  \"min_size\": 80,\n  \"max_size\": 225\n}\n   "
  },
  {
    "client": "phi_4k_instruct",
    "concept": "skis",
    "domain": "size",
    "measurement": "inches",
    "dimension": "height",
    "format": "range",
    "response": "{\n  \"min_size\": 60,\n  \"max_size\": 225\n}\n   "
  },
  {
    "client": "phi_4k_instruct",
    "concept": "skis",
    "domain": "size",
    "measurement": "inches",
    "dimension": "height",
    "format": "range",
    "response": "{\n  \"min_size\": 75,\n  \"max_size\": 225\n}\n   "
  },
  {
    "client": "phi_4k_instruct",
    "concept": "skis",
    "domain": "size",
    "measurement": "inches",
    "dimension": "height",
    "format": "range",
    "response": "{\n  \"min_size\": 60,\n  \"max_size\": 225\n}\n \t\t\t\t\t\t\t\t\t\t\t\t\t\t\t\t\t\t\t"
  },
  {
    "client": "phi_4k_instruct",
    "concept": "skis",
    "domain": "size",
    "measurement": "inches",
    "dimension": "height",
    "format": "range",
    "response": "{\n  \"min_size\": 74,\n  \"max_size\": 225\n}\n   "
  },
  {
    "client": "phi_4k_instruct",
    "concept": "skis",
    "domain": "size",
    "measurement": "inches",
    "dimension": "height",
    "format": "range",
    "response": "{\n  \"min_size\": 72,\n  \"max_size\": 225\n}\n   \t\t\t\t\t\t\t\t\t\t\t\t\t\t\t\t\t"
  },
  {
    "client": "phi_4k_instruct",
    "concept": "skis",
    "domain": "size",
    "measurement": "inches",
    "dimension": "height",
    "format": "range",
    "response": "{\n  \"min_size\": 78,\n  \"max_size\": 225\n}\n \t\t\t\t\t\t\t\t\t\t\t\t\t\t\t\t\t\t\t"
  },
  {
    "client": "phi_4k_instruct",
    "concept": "skis",
    "domain": "size",
    "measurement": "inches",
    "dimension": "height",
    "format": "range",
    "response": "{\n  \"min_size\": 22.0,\n  \"max_size\": 24.0\n}\n   "
  },
  {
    "client": "phi_4k_instruct",
    "concept": "skis",
    "domain": "size",
    "measurement": "inches",
    "dimension": "height",
    "format": "range",
    "response": "{\n  \"min_size\": 60,\n  \"max_size\": 225\n}\n  \t\t\t\t\t\t\t\t\t\t\t\t\t\t\t\t\t\t"
  }
]