[
  {
    "client": "llava_7b_standard",
    "concept": "sheep",
    "domain": "value",
    "measurement": "US dollars",
    "dimension": "monetary_value",
    "format": "range",
    "response": " ```json\n{\n  \"min_value\": 0.1,\n  \"max_value\": 500\n}\n``` "
  },
  {
    "client": "llava_7b_standard",
    "concept": "sheep",
    "domain": "value",
    "measurement": "US dollars",
    "dimension": "monetary_value",
    "format": "range",
    "response": " ```json\n{\n  \"min_value\": 0,\n  \"max_value\": 5000\n}\n``` "
  },
  {
    "client": "llava_7b_standard",
    "concept": "sheep",
    "domain": "value",
    "measurement": "US dollars",
    "dimension": "monetary_value",
    "format": "range",
    "response": " ```json\n{\n  \"min_value\": 0,\n  \"max_value\": 1500\n}\n``` "
  },
  {
    "client": "llava_7b_standard",
    "concept": "sheep",
    "domain": "value",
    "measurement": "US dollars",
    "dimension": "monetary_value",
    "format": "range",
    "response": " ```json\n{\n  \"min_value\": 1,\n  \"max_value\": 500\n}\n``` "
  },
  {
    "client": "llava_7b_standard",
    "concept": "sheep",
    "domain": "value",
    "measurement": "US dollars",
    "dimension": "monetary_value",
    "format": "range",
    "response": " {\n\"min\\_value\": 0,\n\"max\\_value\": 1500\n} "
  },
  {
    "client": "llava_7b_standard",
    "concept": "sheep",
    "domain": "value",
    "measurement": "US dollars",
    "dimension": "monetary_value",
    "format": "range",
    "response": " ```json\n{\n  \"min_value\": 0,\n  \"max_value\": 1000\n}\n```\nNote that the range value for sheep is an estimation and can vary based on factors such as breed, location, and market conditions. Additionally, this estimate does not take into account any specialty or unique wool types that may command higher prices. "
  },
  {
    "client": "llava_7b_standard",
    "concept": "sheep",
    "domain": "value",
    "measurement": "US dollars",
    "dimension": "monetary_value",
    "format": "range",
    "response": " ```json\n{\n  \"min_value\": 10,\n  \"max_value\": 500\n}\n``` "
  },
  {
    "client": "llava_7b_standard",
    "concept": "sheep",
    "domain": "value",
    "measurement": "US dollars",
    "dimension": "monetary_value",
    "format": "range",
    "response": " {\n\"min\\_value\": 0,\n\"max\\_value\": 10000000\n} "
  },
  {
    "client": "llava_7b_standard",
    "concept": "sheep",
    "domain": "value",
    "measurement": "US dollars",
    "dimension": "monetary_value",
    "format": "range",
    "response": " ```json\n{\n  \"min_value\": 0,\n  \"max_value\": 1500\n}\n``` "
  },
  {
    "client": "llava_7b_standard",
    "concept": "sheep",
    "domain": "value",
    "measurement": "US dollars",
    "dimension": "monetary_value",
    "format": "range",
    "response": " ```json\n{\n    \"min_value\": 100,\n    \"max_value\": 500\n}\n``` "
  },
  {
    "client": "llava_7b_standard",
    "concept": "sheep",
    "domain": "value",
    "measurement": "US dollars",
    "dimension": "monetary_value",
    "format": "range",
    "response": " ```json\n{\n  \"min_value\": 0,\n  \"max_value\": 1000\n}\n``` "
  },
  {
    "client": "llava_7b_standard",
    "concept": "sheep",
    "domain": "value",
    "measurement": "US dollars",
    "dimension": "monetary_value",
    "format": "range",
    "response": " ```json\n{\n    \"min_value\": 0,\n    \"max_value\": 300\n}\n``` "
  },
  {
    "client": "llava_7b_standard",
    "concept": "sheep",
    "domain": "value",
    "measurement": "US dollars",
    "dimension": "monetary_value",
    "format": "range",
    "response": " ```json\n{\n   \"min_value\": 0,\n   \"max_value\": 1000\n}\n```\nExplanation: The value of a sheep cannot be less than 0 and more than 1000 in US dollars. "
  },
  {
    "client": "llava_7b_standard",
    "concept": "sheep",
    "domain": "value",
    "measurement": "US dollars",
    "dimension": "monetary_value",
    "format": "range",
    "response": " ```json\n{\n  \"min_value\": 0,\n  \"max_value\": 1000000\n}\n```\nNote: The range provided is a rough estimate and can vary based on factors such as location, breed, and quality of the wool. "
  },
  {
    "client": "llava_7b_standard",
    "concept": "sheep",
    "domain": "value",
    "measurement": "US dollars",
    "dimension": "monetary_value",
    "format": "range",
    "response": " ```json\n{\n  \"min_value\": 10.0,\n  \"max_value\": 200.0\n}\n```\nNote that the range of a typical sheep is not directly related to its woolly nature or price. The min\\_value represents the cost of purchasing a single young sheep (lamb), while the max\\_value represents the average cost of raising and selling a mature sheep for meat or wool. "
  },
  {
    "client": "llava_7b_standard",
    "concept": "sheep",
    "domain": "value",
    "measurement": "US dollars",
    "dimension": "monetary_value",
    "format": "range",
    "response": " ```json\n{\n    \"min_value\": 0,\n    \"max_value\": 500\n}\n``` "
  },
  {
    "client": "llava_7b_standard",
    "concept": "sheep",
    "domain": "value",
    "measurement": "US dollars",
    "dimension": "monetary_value",
    "format": "range",
    "response": " ```json\n{\n    \"min_value\": 0,\n    \"max_value\": 3\n}\n``` "
  },
  {
    "client": "llava_7b_standard",
    "concept": "sheep",
    "domain": "value",
    "measurement": "US dollars",
    "dimension": "monetary_value",
    "format": "range",
    "response": " {\n\"min\\_value\": 0,\n\"max\\_value\": 150\n} "
  },
  {
    "client": "llava_7b_standard",
    "concept": "sheep",
    "domain": "value",
    "measurement": "US dollars",
    "dimension": "monetary_value",
    "format": "range",
    "response": " ```json\n{\n  \"min_value\": 0,\n  \"max_value\": 1000\n}\n``` "
  },
  {
    "client": "llava_7b_standard",
    "concept": "sheep",
    "domain": "value",
    "measurement": "US dollars",
    "dimension": "monetary_value",
    "format": "range",
    "response": " {\n\"min\\_value\": 0,\n\"max\\_value\": 500\n} "
  }
]