[
  {
    "client": "olmo2_13B_instruct",
    "concept": "sheep",
    "domain": "size",
    "measurement": "inches",
    "dimension": "height",
    "format": "range",
    "response": "{\"min_size\": 24.0, \"max_size\": 36.0}"
  },
  {
    "client": "olmo2_13B_instruct",
    "concept": "sheep",
    "domain": "size",
    "measurement": "inches",
    "dimension": "height",
    "format": "range",
    "response": "{\"min_size\": 36.0, \"max_size\": 41.0}"
  },
  {
    "client": "olmo2_13B_instruct",
    "concept": "sheep",
    "domain": "size",
    "measurement": "inches",
    "dimension": "height",
    "format": "range",
    "response": "{\"min_size\": 37.68, \"max_size\": 43.3}"
  },
  {
    "client": "olmo2_13B_instruct",
    "concept": "sheep",
    "domain": "size",
    "measurement": "inches",
    "dimension": "height",
    "format": "range",
    "response": "{\"min_size\": \"36\", \"max_size\": \"41\"}"
  },
  {
    "client": "olmo2_13B_instruct",
    "concept": "sheep",
    "domain": "size",
    "measurement": "inches",
    "dimension": "height",
    "format": "range",
    "response": "{\"min_size\": \"30\", \"max_size\": \"45\"}"
  },
  {
    "client": "olmo2_13B_instruct",
    "concept": "sheep",
    "domain": "size",
    "measurement": "inches",
    "dimension": "height",
    "format": "range",
    "response": "{\"min_size\": 30.0, \"max_size\": 41.0}"
  },
  {
    "client": "olmo2_13B_instruct",
    "concept": "sheep",
    "domain": "size",
    "measurement": "inches",
    "dimension": "height",
    "format": "range",
    "response": "{\"min_size\": 80, \"max_size\": 120}"
  },
  {
    "client": "olmo2_13B_instruct",
    "concept": "sheep",
    "domain": "size",
    "measurement": "inches",
    "dimension": "height",
    "format": "range",
    "response": "{\"min_size\": 36.0,\"max_size\": 41.0}"
  },
  {
    "client": "olmo2_13B_instruct",
    "concept": "sheep",
    "domain": "size",
    "measurement": "inches",
    "dimension": "height",
    "format": "range",
    "response": "{\"min_size\": 35.43, \"max_size\": 41.91}"
  },
  {
    "client": "olmo2_13B_instruct",
    "concept": "sheep",
    "domain": "size",
    "measurement": "inches",
    "dimension": "height",
    "format": "range",
    "response": "{\"min_size\": 37.5,\"max_size\": 41}"
  },
  {
    "client": "olmo2_13B_instruct",
    "concept": "sheep",
    "domain": "size",
    "measurement": "inches",
    "dimension": "height",
    "format": "range",
    "response": "{\"min_size\": 50, \"max_size\": 54}"
  },
  {
    "client": "olmo2_13B_instruct",
    "concept": "sheep",
    "domain": "size",
    "measurement": "inches",
    "dimension": "height",
    "format": "range",
    "response": "{\"min_size\": 34.0, \"max_size\": 41.0}"
  },
  {
    "client": "olmo2_13B_instruct",
    "concept": "sheep",
    "domain": "size",
    "measurement": "inches",
    "dimension": "height",
    "format": "range",
    "response": "{\"min_size\": 90.0, \"max_size\": 120.0}"
  },
  {
    "client": "olmo2_13B_instruct",
    "concept": "sheep",
    "domain": "size",
    "measurement": "inches",
    "dimension": "height",
    "format": "range",
    "response": "{\"min_size\": 35.43, \"max_size\": 41.73}"
  },
  {
    "client": "olmo2_13B_instruct",
    "concept": "sheep",
    "domain": "size",
    "measurement": "inches",
    "dimension": "height",
    "format": "range",
    "response": "{\"min_size\": 35.43, \"max_size\": 41.73}"
  },
  {
    "client": "olmo2_13B_instruct",
    "concept": "sheep",
    "domain": "size",
    "measurement": "inches",
    "dimension": "height",
    "format": "range",
    "response": "{\"min_size\": 50.0, \"max_size\": 53.5}"
  },
  {
    "client": "olmo2_13B_instruct",
    "concept": "sheep",
    "domain": "size",
    "measurement": "inches",
    "dimension": "height",
    "format": "range",
    "response": "{\"min_size\": 30.0, \"max_size\": 53.0}"
  },
  {
    "client": "olmo2_13B_instruct",
    "concept": "sheep",
    "domain": "size",
    "measurement": "inches",
    "dimension": "height",
    "format": "range",
    "response": "{\"min_size\": \"40\", \"max_size\": \"52\"}"
  },
  {
    "client": "olmo2_13B_instruct",
    "concept": "sheep",
    "domain": "size",
    "measurement": "inches",
    "dimension": "height",
    "format": "range",
    "response": "{\"min_size\": 35.43, \"max_size\": 41.73}"
  },
  {
    "client": "olmo2_13B_instruct",
    "concept": "sheep",
    "domain": "size",
    "measurement": "inches",
    "dimension": "height",
    "format": "range",
    "response": "{\"min_size\": 36.0, \"max_size\": 41.0}"
  }
]