[
  {
    "client": "llama31_8b_standard",
    "concept": "car",
    "domain": "size",
    "measurement": "millimeters",
    "dimension": "height",
    "format": "range",
    "response": "{\n  \"min_size\": 1500,\n  \"max_size\": 5500\n}"
  },
  {
    "client": "llama31_8b_standard",
    "concept": "car",
    "domain": "size",
    "measurement": "millimeters",
    "dimension": "height",
    "format": "range",
    "response": "{\n  \"min_size\": 1690,\n  \"max_size\": 5400\n}"
  },
  {
    "client": "llama31_8b_standard",
    "concept": "car",
    "domain": "size",
    "measurement": "millimeters",
    "dimension": "height",
    "format": "range",
    "response": "{\n  \"min_size\": 1445,\n  \"max_size\": 5000\n}"
  },
  {
    "client": "llama31_8b_standard",
    "concept": "car",
    "domain": "size",
    "measurement": "millimeters",
    "dimension": "height",
    "format": "range",
    "response": "{\n  \"min_size\": 1440,\n  \"max_size\": 5151\n}"
  },
  {
    "client": "llama31_8b_standard",
    "concept": "car",
    "domain": "size",
    "measurement": "millimeters",
    "dimension": "height",
    "format": "range",
    "response": "{\n  \"min_size\": 1644,\n  \"max_size\": 5525\n}"
  },
  {
    "client": "llama31_8b_standard",
    "concept": "car",
    "domain": "size",
    "measurement": "millimeters",
    "dimension": "height",
    "format": "range",
    "response": "{\n  \"min_size\": 1600,\n  \"max_size\": 5600\n}"
  },
  {
    "client": "llama31_8b_standard",
    "concept": "car",
    "domain": "size",
    "measurement": "millimeters",
    "dimension": "height",
    "format": "range",
    "response": "{\n  \"min_size\": 1450,\n  \"max_size\": 5500\n}"
  },
  {
    "client": "llama31_8b_standard",
    "concept": "car",
    "domain": "size",
    "measurement": "millimeters",
    "dimension": "height",
    "format": "range",
    "response": "{\n  \"min_size\": 1590,\n  \"max_size\": 5300\n}"
  },
  {
    "client": "llama31_8b_standard",
    "concept": "car",
    "domain": "size",
    "measurement": "millimeters",
    "dimension": "height",
    "format": "range",
    "response": "{\n  \"min_size\": 1440,\n  \"max_size\": 5300\n}"
  },
  {
    "client": "llama31_8b_standard",
    "concept": "car",
    "domain": "size",
    "measurement": "millimeters",
    "dimension": "height",
    "format": "range",
    "response": "{\n  \"min_size\": 1460,\n  \"max_size\": 5700\n}"
  },
  {
    "client": "llama31_8b_standard",
    "concept": "car",
    "domain": "size",
    "measurement": "millimeters",
    "dimension": "height",
    "format": "range",
    "response": "{\n  \"min_size\": 1445,\n  \"max_size\": 5150\n}"
  },
  {
    "client": "llama31_8b_standard",
    "concept": "car",
    "domain": "size",
    "measurement": "millimeters",
    "dimension": "height",
    "format": "range",
    "response": "{\n  \"min_size\": 1730,\n  \"max_size\": 5600\n}"
  },
  {
    "client": "llama31_8b_standard",
    "concept": "car",
    "domain": "size",
    "measurement": "millimeters",
    "dimension": "height",
    "format": "range",
    "response": "{\n  \"min_size\": 1475,\n  \"max_size\": 5520\n}"
  },
  {
    "client": "llama31_8b_standard",
    "concept": "car",
    "domain": "size",
    "measurement": "millimeters",
    "dimension": "height",
    "format": "range",
    "response": "{\n  \"min_size\": 1800,\n  \"max_size\": 5800\n}"
  },
  {
    "client": "llama31_8b_standard",
    "concept": "car",
    "domain": "size",
    "measurement": "millimeters",
    "dimension": "height",
    "format": "range",
    "response": "{\n  \"min_size\": 1575,\n  \"max_size\": 5120\n}"
  },
  {
    "client": "llama31_8b_standard",
    "concept": "car",
    "domain": "size",
    "measurement": "millimeters",
    "dimension": "height",
    "format": "range",
    "response": "{\n    \"min_size\": 1550,\n    \"max_size\": 5300\n}"
  },
  {
    "client": "llama31_8b_standard",
    "concept": "car",
    "domain": "size",
    "measurement": "millimeters",
    "dimension": "height",
    "format": "range",
    "response": "{\n  \"min_size\": 1650,\n  \"max_size\": 5200\n}"
  },
  {
    "client": "llama31_8b_standard",
    "concept": "car",
    "domain": "size",
    "measurement": "millimeters",
    "dimension": "height",
    "format": "range",
    "response": "{\n  \"min_size\": 4200,\n  \"max_size\": 5200\n}"
  },
  {
    "client": "llama31_8b_standard",
    "concept": "car",
    "domain": "size",
    "measurement": "millimeters",
    "dimension": "height",
    "format": "range",
    "response": "{\n    \"min_size\": 1595,\n    \"max_size\": 5700\n}"
  },
  {
    "client": "llama31_8b_standard",
    "concept": "car",
    "domain": "size",
    "measurement": "millimeters",
    "dimension": "height",
    "format": "range",
    "response": "{\n  \"min_size\": 1400,\n  \"max_size\": 5500\n}"
  }
]