[
  {
    "client": "llama31_8b_standard",
    "concept": "toilet",
    "domain": "weight",
    "measurement": "grams",
    "dimension": "weight",
    "format": "range",
    "response": "{\n  \"min_weight\": 2000,\n  \"max_weight\": 8000\n}"
  },
  {
    "client": "llama31_8b_standard",
    "concept": "toilet",
    "domain": "weight",
    "measurement": "grams",
    "dimension": "weight",
    "format": "range",
    "response": "{\n  \"min_weight\": 15000,\n  \"max_weight\": 50000\n}"
  },
  {
    "client": "llama31_8b_standard",
    "concept": "toilet",
    "domain": "weight",
    "measurement": "grams",
    "dimension": "weight",
    "format": "range",
    "response": "{\n  \"min_weight\": 4000,\n  \"max_weight\": 6000\n}"
  },
  {
    "client": "llama31_8b_standard",
    "concept": "toilet",
    "domain": "weight",
    "measurement": "grams",
    "dimension": "weight",
    "format": "range",
    "response": "{\n  \"min_weight\": 10000,\n  \"max_weight\": 30000\n}"
  },
  {
    "client": "llama31_8b_standard",
    "concept": "toilet",
    "domain": "weight",
    "measurement": "grams",
    "dimension": "weight",
    "format": "range",
    "response": "{\n  \"min_weight\": 20000,\n  \"max_weight\": 80000\n}"
  },
  {
    "client": "llama31_8b_standard",
    "concept": "toilet",
    "domain": "weight",
    "measurement": "grams",
    "dimension": "weight",
    "format": "range",
    "response": "{\n  \"min_weight\": 30000,\n  \"max_weight\": 200000\n}"
  },
  {
    "client": "llama31_8b_standard",
    "concept": "toilet",
    "domain": "weight",
    "measurement": "grams",
    "dimension": "weight",
    "format": "range",
    "response": "{\n    \"min_weight\": 5000,\n    \"max_weight\": 40000\n}"
  },
  {
    "client": "llama31_8b_standard",
    "concept": "toilet",
    "domain": "weight",
    "measurement": "grams",
    "dimension": "weight",
    "format": "range",
    "response": "{\n  \"min_weight\": 15000,\n  \"max_weight\": 40000\n}"
  },
  {
    "client": "llama31_8b_standard",
    "concept": "toilet",
    "domain": "weight",
    "measurement": "grams",
    "dimension": "weight",
    "format": "range",
    "response": "{\n  \"min_weight\": 10000,\n  \"max_weight\": 20000\n}"
  },
  {
    "client": "llama31_8b_standard",
    "concept": "toilet",
    "domain": "weight",
    "measurement": "grams",
    "dimension": "weight",
    "format": "range",
    "response": "{\n  \"min_weight\": 45000,\n  \"max_weight\": 50000\n}"
  },
  {
    "client": "llama31_8b_standard",
    "concept": "toilet",
    "domain": "weight",
    "measurement": "grams",
    "dimension": "weight",
    "format": "range",
    "response": "{\n  \"min_weight\": 15,\n  \"max_weight\": 200\n}"
  },
  {
    "client": "llama31_8b_standard",
    "concept": "toilet",
    "domain": "weight",
    "measurement": "grams",
    "dimension": "weight",
    "format": "range",
    "response": "{\n  \"min_weight\": 25000,\n  \"max_weight\": 60000\n}"
  },
  {
    "client": "llama31_8b_standard",
    "concept": "toilet",
    "domain": "weight",
    "measurement": "grams",
    "dimension": "weight",
    "format": "range",
    "response": "{\n  \"min_weight\": 45000,\n  \"max_weight\": 300000\n}"
  },
  {
    "client": "llama31_8b_standard",
    "concept": "toilet",
    "domain": "weight",
    "measurement": "grams",
    "dimension": "weight",
    "format": "range",
    "response": "{\n  \"min_weight\": 5000,\n  \"max_weight\": 20000\n}"
  },
  {
    "client": "llama31_8b_standard",
    "concept": "toilet",
    "domain": "weight",
    "measurement": "grams",
    "dimension": "weight",
    "format": "range",
    "response": "{\n  \"min_weight\": 15000,\n  \"max_weight\": 25000\n}"
  },
  {
    "client": "llama31_8b_standard",
    "concept": "toilet",
    "domain": "weight",
    "measurement": "grams",
    "dimension": "weight",
    "format": "range",
    "response": "{\n  \"min_weight\": 5000,\n  \"max_weight\": 35000\n}"
  },
  {
    "client": "llama31_8b_standard",
    "concept": "toilet",
    "domain": "weight",
    "measurement": "grams",
    "dimension": "weight",
    "format": "range",
    "response": "{\n  \"min_weight\": 10000,\n  \"max_weight\": 50000\n}"
  },
  {
    "client": "llama31_8b_standard",
    "concept": "toilet",
    "domain": "weight",
    "measurement": "grams",
    "dimension": "weight",
    "format": "range",
    "response": "{\n  \"min_weight\": 15000,\n  \"max_weight\": 25000\n}"
  },
  {
    "client": "llama31_8b_standard",
    "concept": "toilet",
    "domain": "weight",
    "measurement": "grams",
    "dimension": "weight",
    "format": "range",
    "response": "{\n  \"min_weight\": 4000,\n  \"max_weight\": 20000\n}"
  },
  {
    "client": "llama31_8b_standard",
    "concept": "toilet",
    "domain": "weight",
    "measurement": "grams",
    "dimension": "weight",
    "format": "range",
    "response": "{\n  \"min_weight\": 5000,\n  \"max_weight\": 20000\n}"
  }
]