[
  {
    "client": "llama_30b_standard",
    "concept": "handbag",
    "domain": "scenario",
    "measurement": "",
    "dimension": "",
    "format": "avg",
    "response": "{\"scenario\":\"carrying money\"}\n"
  },
  {
    "client": "llama_30b_standard",
    "concept": "handbag",
    "domain": "scenario",
    "measurement": "",
    "dimension": "",
    "format": "avg",
    "response": "{\n\"scenario\": \"a woman is walking in the street with a handbag\"\n}\n"
  },
  {
    "client": "llama_30b_standard",
    "concept": "handbag",
    "domain": "scenario",
    "measurement": "",
    "dimension": "",
    "format": "avg",
    "response": "{\"scenario\": \"Woman puts her purse (bag) on the table.\"}\n"
  },
  {
    "client": "llama_30b_standard",
    "concept": "handbag",
    "domain": "scenario",
    "measurement": "",
    "dimension": "",
    "format": "avg",
    "response": "{\"scenario\":\"to carry money\"}\n"
  },
  {
    "client": "llama_30b_standard",
    "concept": "handbag",
    "domain": "scenario",
    "measurement": "",
    "dimension": "",
    "format": "avg",
    "response": "{\n  \"scenario\": \"the handbag is placed on a desk.\"\n}\n"
  },
  {
    "client": "llama_30b_standard",
    "concept": "handbag",
    "domain": "scenario",
    "measurement": "",
    "dimension": "",
    "format": "avg",
    "response": "{\"scenario\":\"You are holding a handbag\"}\n"
  },
  {
    "client": "llama_30b_standard",
    "concept": "handbag",
    "domain": "scenario",
    "measurement": "",
    "dimension": "",
    "format": "avg",
    "response": "{\n  \"scenario\": \"You can put your keys and wallet inside the handbag and take it with you to a party.\"\n}\n"
  },
  {
    "client": "llama_30b_standard",
    "concept": "handbag",
    "domain": "scenario",
    "measurement": "",
    "dimension": "",
    "format": "avg",
    "response": "{\n\"scenario\" : \"Given the handbag\"\n}\n"
  },
  {
    "client": "llama_30b_standard",
    "concept": "handbag",
    "domain": "scenario",
    "measurement": "",
    "dimension": "",
    "format": "avg",
    "response": "{\n  \"scenario\": \"carrying\"\n}\n"
  },
  {
    "client": "llama_30b_standard",
    "concept": "handbag",
    "domain": "scenario",
    "measurement": "",
    "dimension": "",
    "format": "avg",
    "response": "{\n  \"scenario\": \"a handbag can contain a wallet.\"\n}\n"
  },
  {
    "client": "llama_30b_standard",
    "concept": "handbag",
    "domain": "scenario",
    "measurement": "",
    "dimension": "",
    "format": "avg",
    "response": "{\n  \"scenario\": \"The handbag is a container used for carrying money and small personal items or accessories (especially by women).\"\n}\n"
  },
  {
    "client": "llama_30b_standard",
    "concept": "handbag",
    "domain": "scenario",
    "measurement": "",
    "dimension": "",
    "format": "avg",
    "response": "{\n    \"scenario\": \"carrying\"\n}\n"
  },
  {
    "client": "llama_30b_standard",
    "concept": "handbag",
    "domain": "scenario",
    "measurement": "",
    "dimension": "",
    "format": "avg",
    "response": "{\"scenario\":\"I carry my handbag with me everywhere I go.\"}\n"
  },
  {
    "client": "llama_30b_standard",
    "concept": "handbag",
    "domain": "scenario",
    "measurement": "",
    "dimension": "",
    "format": "avg",
    "response": "{\"scenario\" : \"It is a good gift for a friend who likes handbags.\"}\n   \t\t\t\t\t\t\t\t\t\t\t\t\t\t\t\t\t"
  },
  {
    "client": "llama_30b_standard",
    "concept": "handbag",
    "domain": "scenario",
    "measurement": "",
    "dimension": "",
    "format": "avg",
    "response": "{\n  \"scenario\": \"To carry your handbag with you in an airport\"\n}\n"
  },
  {
    "client": "llama_30b_standard",
    "concept": "handbag",
    "domain": "scenario",
    "measurement": "",
    "dimension": "",
    "format": "avg",
    "response": "{\n  \"scenario\": \"It is a handbag\"\n}\n"
  },
  {
    "client": "llama_30b_standard",
    "concept": "handbag",
    "domain": "scenario",
    "measurement": "",
    "dimension": "",
    "format": "avg",
    "response": "{\"scenario\":\"It is used to carry money and small personal items or accessories (especially by women).\"}\n"
  },
  {
    "client": "llama_30b_standard",
    "concept": "handbag",
    "domain": "scenario",
    "measurement": "",
    "dimension": "",
    "format": "avg",
    "response": "{\n\"scenario\": \"You are carrying your handbag in the street. It is stolen from you by a thief.\"\n}\n"
  },
  {
    "client": "llama_30b_standard",
    "concept": "handbag",
    "domain": "scenario",
    "measurement": "",
    "dimension": "",
    "format": "avg",
    "response": "{\n  \"scenario\": \"to go to the party\"\n}\n"
  },
  {
    "client": "llama_30b_standard",
    "concept": "handbag",
    "domain": "scenario",
    "measurement": "",
    "dimension": "",
    "format": "avg",
    "response": "{\n  \"scenario\": \"carrying a handbag\"\n}\n"
  }
]