[
  {
    "client": "llama_30b_standard",
    "concept": "sports ball",
    "domain": "pattern",
    "measurement": "",
    "dimension": "",
    "format": "avg",
    "response": "{\n  \"pattern\": \"ball\",\n  \"pattern\": \"balls\",\n  \"pattern\": \"sports\",\n  \"pattern\": \"game\",\n  \"pattern\": \"games\",\n  \"pattern\": \"hit\",\n  \"pattern\": \"kick\",\n  \"pattern\": \"throw\",\n  \"pattern\": \"object\",\n  \"pattern\": \"round\"\n}\n"
  },
  {
    "client": "llama_30b_standard",
    "concept": "sports ball",
    "domain": "pattern",
    "measurement": "",
    "dimension": "",
    "format": "avg",
    "response": "{\n  \"pattern\": \"sports ball\"\n}\n"
  },
  {
    "client": "llama_30b_standard",
    "concept": "sports ball",
    "domain": "pattern",
    "measurement": "",
    "dimension": "",
    "format": "avg",
    "response": "{\n  \"pattern\": \"sphere\"\n}\n   \t\t\t\t\t\t\t\t\t\t\t\t\t\t\t\t\t"
  },
  {
    "client": "llama_30b_standard",
    "concept": "sports ball",
    "domain": "pattern",
    "measurement": "",
    "dimension": "",
    "format": "avg",
    "response": "{\n  \"pattern\": \"sports ball\"\n}\n"
  },
  {
    "client": "llama_30b_standard",
    "concept": "sports ball",
    "domain": "pattern",
    "measurement": "",
    "dimension": "",
    "format": "avg",
    "response": "{\"pattern\": \"Sports Balls\"}\n"
  },
  {
    "client": "llama_30b_standard",
    "concept": "sports ball",
    "domain": "pattern",
    "measurement": "",
    "dimension": "",
    "format": "avg",
    "response": "{\n  \"pattern\": \"Ball is round in shape\"\n}\n"
  },
  {
    "client": "llama_30b_standard",
    "concept": "sports ball",
    "domain": "pattern",
    "measurement": "",
    "dimension": "",
    "format": "avg",
    "response": "{\n  \"pattern\": \"A round object that is hit or thrown or kicked in games\"\n}\n"
  },
  {
    "client": "llama_30b_standard",
    "concept": "sports ball",
    "domain": "pattern",
    "measurement": "",
    "dimension": "",
    "format": "avg",
    "response": "{\n  \"pattern\" : \"ball\"\n}\n"
  },
  {
    "client": "llama_30b_standard",
    "concept": "sports ball",
    "domain": "pattern",
    "measurement": "",
    "dimension": "",
    "format": "avg",
    "response": "{\n  \"pattern\": \"a ball that is hit or thrown or kicked in games\"\n}\n"
  },
  {
    "client": "llama_30b_standard",
    "concept": "sports ball",
    "domain": "pattern",
    "measurement": "",
    "dimension": "",
    "format": "avg",
    "response": "{\n    \"pattern\": \"A ball that is kicked or thrown in a game.\"\n}\n"
  },
  {
    "client": "llama_30b_standard",
    "concept": "sports ball",
    "domain": "pattern",
    "measurement": "",
    "dimension": "",
    "format": "avg",
    "response": "{\n  \"pattern\": [\n    \"Basketball\",\n    \"Baseball\",\n    \"Tennis Ball\",\n    \"Football\"\n  ]\n}\n"
  },
  {
    "client": "llama_30b_standard",
    "concept": "sports ball",
    "domain": "pattern",
    "measurement": "",
    "dimension": "",
    "format": "avg",
    "response": "{\n  \"pattern\": \"ball\"\n}\n "
  },
  {
    "client": "llama_30b_standard",
    "concept": "sports ball",
    "domain": "pattern",
    "measurement": "",
    "dimension": "",
    "format": "avg",
    "response": "{\n  \"pattern\": \"The ball is round.\"\n}\n"
  },
  {
    "client": "llama_30b_standard",
    "concept": "sports ball",
    "domain": "pattern",
    "measurement": "",
    "dimension": "",
    "format": "avg",
    "response": "{\n  \"pattern\": \"sports_ball\"\n}\n"
  },
  {
    "client": "llama_30b_standard",
    "concept": "sports ball",
    "domain": "pattern",
    "measurement": "",
    "dimension": "",
    "format": "avg",
    "response": "{\n  \"pattern\": \"I am a soccer ball\"\n}\n"
  },
  {
    "client": "llama_30b_standard",
    "concept": "sports ball",
    "domain": "pattern",
    "measurement": "",
    "dimension": "",
    "format": "avg",
    "response": "{\"pattern\": \"A round object that is hit or thrown or kicked in games.\"}\n"
  },
  {
    "client": "llama_30b_standard",
    "concept": "sports ball",
    "domain": "pattern",
    "measurement": "",
    "dimension": "",
    "format": "avg",
    "response": "{\n  \"pattern\": \"Ball\"\n}\n"
  },
  {
    "client": "llama_30b_standard",
    "concept": "sports ball",
    "domain": "pattern",
    "measurement": "",
    "dimension": "",
    "format": "avg",
    "response": "{\n  \"pattern\": \"a ball is a sports ball\"\n}\n"
  },
  {
    "client": "llama_30b_standard",
    "concept": "sports ball",
    "domain": "pattern",
    "measurement": "",
    "dimension": "",
    "format": "avg",
    "response": "{\"pattern\":\"a ball used in various games and sports\"}\n    "
  },
  {
    "client": "llama_30b_standard",
    "concept": "sports ball",
    "domain": "pattern",
    "measurement": "",
    "dimension": "",
    "format": "avg",
    "response": "{\n  \"pattern\": \"ball (used in a game) is a round object that is hit, thrown, or kicked (like a baseball or basketball)\"\n}\n"
  }
]