[
  {
    "client": "llama_30b_standard",
    "concept": "refrigerator",
    "domain": "context",
    "measurement": "",
    "dimension": "",
    "format": "avg",
    "response": "{\n  \"context\": \"a kitchen\",\n  \"context\": \"a house\",\n  \"context\": \"an apartment\",\n  \"context\": \"a hotel\",\n  \"context\": \"a restaurant\",\n  \"context\": \"a bar\",\n  \"context\": \"a grocery store\",\n  \"context\": \"a mall\",\n  \"context\": \"a department store\",\n  \"context\": \"a business\",\n  \"context\": \"an office\",\n  \"context\": \"a home\",\n  \"context\": \"a bedroom\",\n  \"context\": \"a living room\",\n  \"context\": \"a family room\",\n  \"context\": \"a dining room\",\n  \"context\": \"a bathroom\",\n  \"context\": \"a kitchen\",\n  \"context\": \"a garage\",\n  \"context\": \"a laundry room\"\n}\n"
  },
  {
    "client": "llama_30b_standard",
    "concept": "refrigerator",
    "domain": "context",
    "measurement": "",
    "dimension": "",
    "format": "avg",
    "response": "{\n  \"context\": \"a kitchen\"\n}\n"
  },
  {
    "client": "llama_30b_standard",
    "concept": "refrigerator",
    "domain": "context",
    "measurement": "",
    "dimension": "",
    "format": "avg",
    "response": "{\"context\":\"home\"}\n"
  },
  {
    "client": "llama_30b_standard",
    "concept": "refrigerator",
    "domain": "context",
    "measurement": "",
    "dimension": "",
    "format": "avg",
    "response": "{\n  \"context\": \"context\"\n}\n"
  },
  {
    "client": "llama_30b_standard",
    "concept": "refrigerator",
    "domain": "context",
    "measurement": "",
    "dimension": "",
    "format": "avg",
    "response": "{\"context\":\"context1\",\"context2\":\"context2\"}\n"
  },
  {
    "client": "llama_30b_standard",
    "concept": "refrigerator",
    "domain": "context",
    "measurement": "",
    "dimension": "",
    "format": "avg",
    "response": "{\n  \"context\": \"kitchen\"\n}\n"
  },
  {
    "client": "llama_30b_standard",
    "concept": "refrigerator",
    "domain": "context",
    "measurement": "",
    "dimension": "",
    "format": "avg",
    "response": "{\"context\": \"kitchen\"}\n"
  },
  {
    "client": "llama_30b_standard",
    "concept": "refrigerator",
    "domain": "context",
    "measurement": "",
    "dimension": "",
    "format": "avg",
    "response": "{\n  \"context\": \"a room\",\n  \"entities\": [\n    {\n      \"entity\": \"refrigerator\",\n      \"start\": 5,\n      \"end\": 16\n    },\n    {\n      \"entity\": \"room\",\n      \"start\": 17,\n      \"end\": 21\n    }\n  ],\n  \"intent\": \"actions.intent.TEXT\",\n  \"language_code\": \"en\"\n}\n"
  },
  {
    "client": "llama_30b_standard",
    "concept": "refrigerator",
    "domain": "context",
    "measurement": "",
    "dimension": "",
    "format": "avg",
    "response": "{\n  \"context\": \"home appliance\",\n  \"context\": \"appliance\",\n  \"context\": \"kitchen appliance\",\n  \"context\": \"domestic appliance\",\n  \"context\": \"white goods\",\n  \"context\": \"large appliance\",\n  \"context\": \"major appliance\",\n  \"context\": \"domestic device\",\n  \"context\": \"electrical appliance\",\n  \"context\": \"electrical device\",\n  \"context\": \"electronic device\",\n  \"context\": \"device\",\n  \"context\": \"machine\",\n  \"context\": \"technology\",\n  \"context\": \"electronics\",\n  \"context\": \"electrical engineering\",\n  \"context\": \"domestic technology\",\n  \"context\": \"domestic engineering\",\n  \"context\": \"kitchen technology\",\n  \"context\": \"kitchen engineering\",\n  \"context\": \"kitchen appliances\",\n  \"context\": \"appliances\",\n  \"context\": \"kitchenware\",\n  \"context\": \"large appliances\",\n  \"context\": \"major appliances\",\n  \"context\": \"domestic appliances\",\n  \"context\": \"white goods\",\n  \"context\": \"electrical goods\",\n  \"context\": \"electrical equipment\",\n  \"context\": \"kitchen equipment\"\n}\n"
  },
  {
    "client": "llama_30b_standard",
    "concept": "refrigerator",
    "domain": "context",
    "measurement": "",
    "dimension": "",
    "format": "avg",
    "response": "{\"context\":\"kitchen\",\"context\":\"household\",\"context\":\"home\",\"context\":\"house\"}\n   "
  },
  {
    "client": "llama_30b_standard",
    "concept": "refrigerator",
    "domain": "context",
    "measurement": "",
    "dimension": "",
    "format": "avg",
    "response": "{\n  \"context\" : \"kitchen\"\n}\n"
  },
  {
    "client": "llama_30b_standard",
    "concept": "refrigerator",
    "domain": "context",
    "measurement": "",
    "dimension": "",
    "format": "avg",
    "response": "{\n  \"context\": \"kitchen\"\n}\n"
  },
  {
    "client": "llama_30b_standard",
    "concept": "refrigerator",
    "domain": "context",
    "measurement": "",
    "dimension": "",
    "format": "avg",
    "response": "{\n  \"context\": \"home\",\n  \"context\": \"kitchen\",\n  \"context\": \"fridge\"\n}\n"
  },
  {
    "client": "llama_30b_standard",
    "concept": "refrigerator",
    "domain": "context",
    "measurement": "",
    "dimension": "",
    "format": "avg",
    "response": "{\n    \"context\" : \"kitchen\",\n    \"text\" : \"kitchen\",\n    \"id\" : \"0000000000000000000000000000000000000000000000000000000000000000\"\n}\n"
  },
  {
    "client": "llama_30b_standard",
    "concept": "refrigerator",
    "domain": "context",
    "measurement": "",
    "dimension": "",
    "format": "avg",
    "response": "{\n  \"context\": \"kitchen\"\n}\n"
  },
  {
    "client": "llama_30b_standard",
    "concept": "refrigerator",
    "domain": "context",
    "measurement": "",
    "dimension": "",
    "format": "avg",
    "response": "{\n  \"context\": \"the context of the refrigerator\"\n}\n"
  },
  {
    "client": "llama_30b_standard",
    "concept": "refrigerator",
    "domain": "context",
    "measurement": "",
    "dimension": "",
    "format": "avg",
    "response": "{\"context\":\"the kitchen\"}\n"
  },
  {
    "client": "llama_30b_standard",
    "concept": "refrigerator",
    "domain": "context",
    "measurement": "",
    "dimension": "",
    "format": "avg",
    "response": "{\n  \"context\": \"kitchen\"\n}\n"
  },
  {
    "client": "llama_30b_standard",
    "concept": "refrigerator",
    "domain": "context",
    "measurement": "",
    "dimension": "",
    "format": "avg",
    "response": "{\n  \"context\": [\n    \"home\",\n    \"kitchen\",\n    \"fridge\",\n    \"fridge\",\n    \"fridge\"\n  ]\n}\n"
  },
  {
    "client": "llama_30b_standard",
    "concept": "refrigerator",
    "domain": "context",
    "measurement": "",
    "dimension": "",
    "format": "avg",
    "response": "{\n  \"context\": \"food\"\n}\n"
  }
]